{
  "status": "ONLINE",
  "last_updated": 1764174375936,
  "market": {
    "price": 779,
    "trend": "📉 TURUN",
    "high": 817,
    "low": 740,
    "vol": 83016
  },
  "orderBook": {
    "bids": [
      {
        "p": 778,
        "a": 163
      },
      {
        "p": 777,
        "a": 731
      },
      {
        "p": 776,
        "a": 806
      },
      {
        "p": 775,
        "a": 779
      },
      {
        "p": 775,
        "a": 1007
      }
    ],
    "asks": [
      {
        "p": 779,
        "a": 958
      },
      {
        "p": 780,
        "a": 910
      },
      {
        "p": 781,
        "a": 544
      },
      {
        "p": 782,
        "a": 747
      },
      {
        "p": 782,
        "a": 49
      }
    ]
  },
  "trades": [
    {
      "t": "16.26.15",
      "type": "BUY",
      "p": 779,
      "a": 193
    },
    {
      "t": "16.26.10",
      "type": "BUY",
      "p": 779,
      "a": 292
    },
    {
      "t": "16.25.50",
      "type": "SELL",
      "p": 779,
      "a": 180
    },
    {
      "t": "16.25.40",
      "type": "SELL",
      "p": 779,
      "a": 158
    },
    {
      "t": "16.25.30",
      "type": "BUY",
      "p": 779,
      "a": 380
    },
    {
      "t": "16.25.25",
      "type": "BUY",
      "p": 779,
      "a": 137
    },
    {
      "t": "16.25.20",
      "type": "BUY",
      "p": 779,
      "a": 50
    },
    {
      "t": "16.25.10",
      "type": "SELL",
      "p": 779,
      "a": 441
    },
    {
      "t": "16.25.00",
      "type": "SELL",
      "p": 779,
      "a": 247
    },
    {
      "t": "16.24.55",
      "type": "BUY",
      "p": 779,
      "a": 185
    }
  ],
  "history": [
    {
      "t": "16.11.45",
      "p": 779
    },
    {
      "t": "16.11.50",
      "p": 779
    },
    {
      "t": "16.11.55",
      "p": 779
    },
    {
      "t": "16.12.10",
      "p": 779
    },
    {
      "t": "16.12.40",
      "p": 779
    },
    {
      "t": "16.12.45",
      "p": 779
    },
    {
      "t": "16.13.40",
      "p": 779
    },
    {
      "t": "16.13.50",
      "p": 779
    },
    {
      "t": "16.14.25",
      "p": 779
    },
    {
      "t": "16.14.35",
      "p": 779
    },
    {
      "t": "16.15.10",
      "p": 779
    },
    {
      "t": "16.15.30",
      "p": 779
    },
    {
      "t": "16.15.35",
      "p": 779
    },
    {
      "t": "16.15.50",
      "p": 779
    },
    {
      "t": "16.16.00",
      "p": 779
    },
    {
      "t": "16.16.30",
      "p": 779
    },
    {
      "t": "16.16.45",
      "p": 779
    },
    {
      "t": "16.17.05",
      "p": 779
    },
    {
      "t": "16.17.20",
      "p": 779
    },
    {
      "t": "16.17.30",
      "p": 779
    },
    {
      "t": "16.17.45",
      "p": 779
    },
    {
      "t": "16.18.05",
      "p": 779
    },
    {
      "t": "16.18.10",
      "p": 779
    },
    {
      "t": "16.18.20",
      "p": 779
    },
    {
      "t": "16.19.00",
      "p": 779
    },
    {
      "t": "16.19.05",
      "p": 779
    },
    {
      "t": "16.19.15",
      "p": 779
    },
    {
      "t": "16.19.25",
      "p": 779
    },
    {
      "t": "16.19.50",
      "p": 779
    },
    {
      "t": "16.20.15",
      "p": 779
    },
    {
      "t": "16.20.30",
      "p": 779
    },
    {
      "t": "16.20.35",
      "p": 779
    },
    {
      "t": "16.20.50",
      "p": 779
    },
    {
      "t": "16.20.55",
      "p": 779
    },
    {
      "t": "16.21.00",
      "p": 779
    },
    {
      "t": "16.21.10",
      "p": 779
    },
    {
      "t": "16.21.20",
      "p": 779
    },
    {
      "t": "16.21.25",
      "p": 779
    },
    {
      "t": "16.21.35",
      "p": 779
    },
    {
      "t": "16.21.45",
      "p": 779
    },
    {
      "t": "16.22.30",
      "p": 779
    },
    {
      "t": "16.22.50",
      "p": 779
    },
    {
      "t": "16.23.35",
      "p": 779
    },
    {
      "t": "16.23.50",
      "p": 779
    },
    {
      "t": "16.24.15",
      "p": 779
    },
    {
      "t": "16.24.35",
      "p": 779
    },
    {
      "t": "16.24.45",
      "p": 779
    },
    {
      "t": "16.25.00",
      "p": 779
    },
    {
      "t": "16.25.05",
      "p": 779
    },
    {
      "t": "16.26.00",
      "p": 779
    }
  ],
  "stats": {
    "total_investors": 1
  }
}