{
  "status": "ONLINE",
  "last_updated": 1764186559281,
  "market": {
    "price": 779,
    "trend": "📉 TURUN",
    "high": 817,
    "low": 740,
    "vol": 82564
  },
  "orderBook": {
    "bids": [
      {
        "p": 778,
        "a": 287
      },
      {
        "p": 777,
        "a": 16
      },
      {
        "p": 776,
        "a": 989
      },
      {
        "p": 775,
        "a": 349
      },
      {
        "p": 775,
        "a": 502
      }
    ],
    "asks": [
      {
        "p": 779,
        "a": 100
      },
      {
        "p": 780,
        "a": 641
      },
      {
        "p": 781,
        "a": 944
      },
      {
        "p": 782,
        "a": 380
      },
      {
        "p": 782,
        "a": 211
      }
    ]
  },
  "trades": [
    {
      "t": "19.49.14",
      "type": "BUY",
      "p": 779,
      "a": 459
    },
    {
      "t": "19.49.09",
      "type": "BUY",
      "p": 779,
      "a": 340
    },
    {
      "t": "19.49.04",
      "type": "BUY",
      "p": 779,
      "a": 246
    },
    {
      "t": "19.48.59",
      "type": "SELL",
      "p": 779,
      "a": 49
    },
    {
      "t": "19.48.54",
      "type": "BUY",
      "p": 779,
      "a": 481
    },
    {
      "t": "19.48.39",
      "type": "BUY",
      "p": 779,
      "a": 239
    },
    {
      "t": "19.48.29",
      "type": "BUY",
      "p": 779,
      "a": 83
    },
    {
      "t": "19.48.24",
      "type": "SELL",
      "p": 779,
      "a": 273
    },
    {
      "t": "19.48.14",
      "type": "SELL",
      "p": 779,
      "a": 496
    },
    {
      "t": "19.48.04",
      "type": "BUY",
      "p": 779,
      "a": 460
    }
  ],
  "history": [
    {
      "t": "19.38.38",
      "p": 779
    },
    {
      "t": "19.38.43",
      "p": 779
    },
    {
      "t": "19.39.08",
      "p": 779
    },
    {
      "t": "19.39.23",
      "p": 779
    },
    {
      "t": "19.39.28",
      "p": 779
    },
    {
      "t": "19.39.43",
      "p": 779
    },
    {
      "t": "19.40.23",
      "p": 779
    },
    {
      "t": "19.40.33",
      "p": 779
    },
    {
      "t": "19.40.48",
      "p": 779
    },
    {
      "t": "19.40.58",
      "p": 779
    },
    {
      "t": "19.41.08",
      "p": 779
    },
    {
      "t": "19.41.13",
      "p": 779
    },
    {
      "t": "19.41.18",
      "p": 779
    },
    {
      "t": "19.41.38",
      "p": 779
    },
    {
      "t": "19.41.43",
      "p": 779
    },
    {
      "t": "19.41.48",
      "p": 779
    },
    {
      "t": "19.41.53",
      "p": 779
    },
    {
      "t": "19.42.24",
      "p": 779
    },
    {
      "t": "19.42.34",
      "p": 779
    },
    {
      "t": "19.42.39",
      "p": 779
    },
    {
      "t": "19.43.14",
      "p": 779
    },
    {
      "t": "19.43.44",
      "p": 779
    },
    {
      "t": "19.43.49",
      "p": 779
    },
    {
      "t": "19.43.54",
      "p": 779
    },
    {
      "t": "19.43.59",
      "p": 779
    },
    {
      "t": "19.44.04",
      "p": 779
    },
    {
      "t": "19.44.19",
      "p": 779
    },
    {
      "t": "19.44.34",
      "p": 779
    },
    {
      "t": "19.44.44",
      "p": 779
    },
    {
      "t": "19.44.59",
      "p": 779
    },
    {
      "t": "19.45.04",
      "p": 779
    },
    {
      "t": "19.45.29",
      "p": 779
    },
    {
      "t": "19.45.49",
      "p": 779
    },
    {
      "t": "19.46.14",
      "p": 779
    },
    {
      "t": "19.46.54",
      "p": 779
    },
    {
      "t": "19.47.09",
      "p": 779
    },
    {
      "t": "19.47.14",
      "p": 779
    },
    {
      "t": "19.47.19",
      "p": 779
    },
    {
      "t": "19.47.49",
      "p": 779
    },
    {
      "t": "19.47.59",
      "p": 779
    },
    {
      "t": "19.48.09",
      "p": 779
    },
    {
      "t": "19.48.19",
      "p": 779
    },
    {
      "t": "19.48.24",
      "p": 779
    },
    {
      "t": "19.48.29",
      "p": 779
    },
    {
      "t": "19.48.34",
      "p": 779
    },
    {
      "t": "19.48.44",
      "p": 779
    },
    {
      "t": "19.48.54",
      "p": 779
    },
    {
      "t": "19.48.59",
      "p": 779
    },
    {
      "t": "19.49.09",
      "p": 779
    },
    {
      "t": "19.49.19",
      "p": 779
    }
  ],
  "stats": {
    "total_investors": 1
  }
}