{
  "status": "MARKET_OPEN",
  "last_updated": 1764509376353,
  "readable_time": "30/11/2025, 13.29.36",
  "market": {
    "price": 950,
    "trend": "📉 BEARISH (News)",
    "high": 1064,
    "low": 836,
    "vol": 5965453,
    "mcap": 9500000000,
    "news": {
      "headline": "Isu regulasi krypto global membuat investor retail panik.",
      "type": "BAD",
      "timestamp": 1764509296246
    }
  },
  "leaderboard": [
    {
      "name": "Big Boss",
      "wealth": 1000949989999
    }
  ],
  "orderBook": {
    "bids": [
      {
        "p": 948,
        "a": 619
      },
      {
        "p": 946,
        "a": 4781
      },
      {
        "p": 944,
        "a": 475
      },
      {
        "p": 942,
        "a": 2114
      },
      {
        "p": 940,
        "a": 3999
      },
      {
        "p": 938,
        "a": 129
      },
      {
        "p": 936,
        "a": 3393
      },
      {
        "p": 934,
        "a": 941
      }
    ],
    "asks": [
      {
        "p": 951,
        "a": 2490
      },
      {
        "p": 953,
        "a": 4448
      },
      {
        "p": 955,
        "a": 4344
      },
      {
        "p": 957,
        "a": 2112
      },
      {
        "p": 959,
        "a": 4853
      },
      {
        "p": 961,
        "a": 4956
      },
      {
        "p": 963,
        "a": 4941
      },
      {
        "p": 965,
        "a": 1622
      }
    ]
  },
  "trades": [
    {
      "t": "13.29.36",
      "type": "BUY",
      "p": 950,
      "a": 1650
    },
    {
      "t": "13.29.26",
      "type": "SELL",
      "p": 950,
      "a": 593
    },
    {
      "t": "13.29.16",
      "type": "SELL",
      "p": 950,
      "a": 435
    },
    {
      "t": "13.29.06",
      "type": "SELL",
      "p": 950,
      "a": 985
    },
    {
      "t": "13.28.56",
      "type": "BUY",
      "p": 950,
      "a": 362
    },
    {
      "t": "13.28.51",
      "type": "BUY",
      "p": 950,
      "a": 1510
    },
    {
      "t": "13.28.46",
      "type": "BUY",
      "p": 950,
      "a": 290
    },
    {
      "t": "13.28.41",
      "type": "BUY",
      "p": 950,
      "a": 558
    },
    {
      "t": "13.28.36",
      "type": "BUY",
      "p": 950,
      "a": 699
    },
    {
      "t": "13.28.26",
      "type": "BUY",
      "p": 950,
      "a": 619
    },
    {
      "t": "13.28.21",
      "type": "BUY",
      "p": 950,
      "a": 1854
    },
    {
      "t": "13.28.16",
      "type": "SELL",
      "p": 1000,
      "a": 1458
    },
    {
      "t": "13.28.01",
      "type": "BUY",
      "p": 1000,
      "a": 576
    },
    {
      "t": "13.27.51",
      "type": "BUY",
      "p": 1000,
      "a": 120
    },
    {
      "t": "13.27.36",
      "type": "SELL",
      "p": 1000,
      "a": 1644
    }
  ],
  "history": [
    {
      "t": "13.15.28",
      "p": 1382
    },
    {
      "t": "13.15.48",
      "p": 1423
    },
    {
      "t": "13.15.53",
      "p": 1423
    },
    {
      "t": "13.16.08",
      "p": 1423
    },
    {
      "t": "13.16.23",
      "p": 1423
    },
    {
      "t": "13.16.28",
      "p": 1423
    },
    {
      "t": "13.16.43",
      "p": 1423
    },
    {
      "t": "13.16.48",
      "p": 1423
    },
    {
      "t": "13.16.53",
      "p": 1423
    },
    {
      "t": "13.17.03",
      "p": 1423
    },
    {
      "t": "13.17.18",
      "p": 1423
    },
    {
      "t": "13.17.23",
      "p": 1423
    },
    {
      "t": "13.17.28",
      "p": 1423
    },
    {
      "t": "13.17.38",
      "p": 1423
    },
    {
      "t": "13.17.48",
      "p": 1423
    },
    {
      "t": "13.17.53",
      "p": 1423
    },
    {
      "t": "13.17.58",
      "p": 1423
    },
    {
      "t": "13.18.06",
      "p": 1423
    },
    {
      "t": "13.18.11",
      "p": 1423
    },
    {
      "t": "13.18.16",
      "p": 1423
    },
    {
      "t": "13.18.45",
      "p": 1423
    },
    {
      "t": "13.19.20",
      "p": 1423
    },
    {
      "t": "13.19.25",
      "p": 1423
    },
    {
      "t": "13.19.30",
      "p": 1423
    },
    {
      "t": "13.19.45",
      "p": 1423
    },
    {
      "t": "13.20.10",
      "p": 1423
    },
    {
      "t": "13.20.20",
      "p": 1423
    },
    {
      "t": "13.20.30",
      "p": 1423
    },
    {
      "t": "13.20.35",
      "p": 1423
    },
    {
      "t": "13.20.45",
      "p": 1423
    },
    {
      "t": "13.20.50",
      "p": 1423
    },
    {
      "t": "13.20.55",
      "p": 1423
    },
    {
      "t": "13.21.00",
      "p": 1423
    },
    {
      "t": "13.21.15",
      "p": 1000
    },
    {
      "t": "13.21.25",
      "p": 1000
    },
    {
      "t": "13.21.30",
      "p": 1000
    },
    {
      "t": "13.21.35",
      "p": 1000
    },
    {
      "t": "13.21.50",
      "p": 1000
    },
    {
      "t": "13.21.55",
      "p": 1000
    },
    {
      "t": "13.22.05",
      "p": 1000
    },
    {
      "t": "13.22.10",
      "p": 1000
    },
    {
      "t": "13.22.15",
      "p": 1000
    },
    {
      "t": "13.22.20",
      "p": 1000
    },
    {
      "t": "13.22.25",
      "p": 1000
    },
    {
      "t": "13.22.35",
      "p": 1000
    },
    {
      "t": "13.22.40",
      "p": 1000
    },
    {
      "t": "13.22.50",
      "p": 1000
    },
    {
      "t": "13.27.36",
      "p": 1000
    },
    {
      "t": "13.28.06",
      "p": 1000
    },
    {
      "t": "13.28.11",
      "p": 1000
    },
    {
      "t": "13.28.16",
      "p": 1000
    },
    {
      "t": "13.28.21",
      "p": 950
    },
    {
      "t": "13.28.31",
      "p": 950
    },
    {
      "t": "13.28.41",
      "p": 950
    },
    {
      "t": "13.28.51",
      "p": 950
    },
    {
      "t": "13.28.56",
      "p": 950
    },
    {
      "t": "13.29.01",
      "p": 950
    },
    {
      "t": "13.29.11",
      "p": 950
    },
    {
      "t": "13.29.31",
      "p": 950
    },
    {
      "t": "13.29.36",
      "p": 950
    }
  ],
  "stats": {
    "total_investors": 1
  }
}