{
  "status": "ONLINE",
  "last_updated": 1764190216544,
  "market": {
    "price": 779,
    "trend": "📉 TURUN",
    "high": 817,
    "low": 740,
    "vol": 79404
  },
  "orderBook": {
    "bids": [
      {
        "p": 778,
        "a": 124
      },
      {
        "p": 777,
        "a": 787
      },
      {
        "p": 776,
        "a": 899
      },
      {
        "p": 775,
        "a": 707
      },
      {
        "p": 775,
        "a": 690
      }
    ],
    "asks": [
      {
        "p": 779,
        "a": 843
      },
      {
        "p": 780,
        "a": 355
      },
      {
        "p": 781,
        "a": 661
      },
      {
        "p": 782,
        "a": 46
      },
      {
        "p": 782,
        "a": 263
      }
    ]
  },
  "trades": [
    {
      "t": "20.50.16",
      "type": "SELL",
      "p": 779,
      "a": 444
    },
    {
      "t": "20.50.11",
      "type": "BUY",
      "p": 779,
      "a": 422
    },
    {
      "t": "20.50.06",
      "type": "BUY",
      "p": 779,
      "a": 291
    },
    {
      "t": "20.50.01",
      "type": "SELL",
      "p": 779,
      "a": 175
    },
    {
      "t": "20.49.56",
      "type": "SELL",
      "p": 779,
      "a": 194
    },
    {
      "t": "20.49.51",
      "type": "BUY",
      "p": 779,
      "a": 427
    },
    {
      "t": "20.49.36",
      "type": "SELL",
      "p": 779,
      "a": 500
    },
    {
      "t": "20.49.31",
      "type": "BUY",
      "p": 779,
      "a": 476
    },
    {
      "t": "20.49.26",
      "type": "BUY",
      "p": 779,
      "a": 478
    },
    {
      "t": "20.49.16",
      "type": "BUY",
      "p": 779,
      "a": 494
    }
  ],
  "history": [
    {
      "t": "20.38.26",
      "p": 779
    },
    {
      "t": "20.38.56",
      "p": 779
    },
    {
      "t": "20.39.16",
      "p": 779
    },
    {
      "t": "20.39.36",
      "p": 779
    },
    {
      "t": "20.39.46",
      "p": 779
    },
    {
      "t": "20.40.21",
      "p": 779
    },
    {
      "t": "20.40.26",
      "p": 779
    },
    {
      "t": "20.40.46",
      "p": 779
    },
    {
      "t": "20.40.56",
      "p": 779
    },
    {
      "t": "20.41.01",
      "p": 779
    },
    {
      "t": "20.41.26",
      "p": 779
    },
    {
      "t": "20.41.36",
      "p": 779
    },
    {
      "t": "20.41.51",
      "p": 779
    },
    {
      "t": "20.42.01",
      "p": 779
    },
    {
      "t": "20.42.31",
      "p": 779
    },
    {
      "t": "20.42.36",
      "p": 779
    },
    {
      "t": "20.42.56",
      "p": 779
    },
    {
      "t": "20.43.01",
      "p": 779
    },
    {
      "t": "20.43.06",
      "p": 779
    },
    {
      "t": "20.43.16",
      "p": 779
    },
    {
      "t": "20.43.21",
      "p": 779
    },
    {
      "t": "20.43.26",
      "p": 779
    },
    {
      "t": "20.43.41",
      "p": 779
    },
    {
      "t": "20.43.46",
      "p": 779
    },
    {
      "t": "20.44.01",
      "p": 779
    },
    {
      "t": "20.44.26",
      "p": 779
    },
    {
      "t": "20.44.31",
      "p": 779
    },
    {
      "t": "20.45.11",
      "p": 779
    },
    {
      "t": "20.45.21",
      "p": 779
    },
    {
      "t": "20.45.36",
      "p": 779
    },
    {
      "t": "20.46.06",
      "p": 779
    },
    {
      "t": "20.46.21",
      "p": 779
    },
    {
      "t": "20.46.51",
      "p": 779
    },
    {
      "t": "20.46.56",
      "p": 779
    },
    {
      "t": "20.47.31",
      "p": 779
    },
    {
      "t": "20.47.36",
      "p": 779
    },
    {
      "t": "20.47.41",
      "p": 779
    },
    {
      "t": "20.48.01",
      "p": 779
    },
    {
      "t": "20.48.16",
      "p": 779
    },
    {
      "t": "20.48.21",
      "p": 779
    },
    {
      "t": "20.48.26",
      "p": 779
    },
    {
      "t": "20.48.31",
      "p": 779
    },
    {
      "t": "20.48.36",
      "p": 779
    },
    {
      "t": "20.48.51",
      "p": 779
    },
    {
      "t": "20.49.01",
      "p": 779
    },
    {
      "t": "20.49.16",
      "p": 779
    },
    {
      "t": "20.49.21",
      "p": 779
    },
    {
      "t": "20.49.51",
      "p": 779
    },
    {
      "t": "20.50.06",
      "p": 779
    },
    {
      "t": "20.50.11",
      "p": 779
    }
  ],
  "stats": {
    "total_investors": 1
  }
}