{
  "status": "MARKET_OPEN",
  "last_updated": 1764682150600,
  "readable_time": "2/12/2025, 13.29.10",
  "market": {
    "price": 4320,
    "trend": "📈 BULLISH (News)",
    "high": 4838,
    "low": 3801,
    "vol": 2308821,
    "mcap": 43200000000,
    "news": {
      "headline": "Sistem mining $ARA di-upgrade menjadi lebih efisien dan hemat energi.",
      "type": "GOOD",
      "timestamp": 1764682020526
    }
  },
  "leaderboard": [
    {
      "name": "Big Boss",
      "wealth": 1004332530749
    }
  ],
  "orderBook": {
    "bids": [
      {
        "p": 4311,
        "a": 4664
      },
      {
        "p": 4302,
        "a": 1713
      },
      {
        "p": 4294,
        "a": 2347
      },
      {
        "p": 4285,
        "a": 1717
      },
      {
        "p": 4276,
        "a": 252
      },
      {
        "p": 4268,
        "a": 3343
      },
      {
        "p": 4259,
        "a": 1724
      },
      {
        "p": 4250,
        "a": 4746
      }
    ],
    "asks": [
      {
        "p": 4328,
        "a": 4806
      },
      {
        "p": 4337,
        "a": 1811
      },
      {
        "p": 4345,
        "a": 294
      },
      {
        "p": 4354,
        "a": 371
      },
      {
        "p": 4363,
        "a": 1411
      },
      {
        "p": 4371,
        "a": 1724
      },
      {
        "p": 4380,
        "a": 2217
      },
      {
        "p": 4389,
        "a": 725
      }
    ]
  },
  "trades": [
    {
      "t": "13.29.10",
      "type": "SELL",
      "p": 4320,
      "a": 1544
    },
    {
      "t": "13.29.05",
      "type": "SELL",
      "p": 4320,
      "a": 203
    },
    {
      "t": "13.28.55",
      "type": "BUY",
      "p": 4320,
      "a": 1018
    },
    {
      "t": "13.28.50",
      "type": "BUY",
      "p": 4320,
      "a": 104
    },
    {
      "t": "13.28.45",
      "type": "BUY",
      "p": 4320,
      "a": 1968
    },
    {
      "t": "13.28.40",
      "type": "BUY",
      "p": 4320,
      "a": 1528
    },
    {
      "t": "13.28.35",
      "type": "SELL",
      "p": 4320,
      "a": 1348
    },
    {
      "t": "13.28.30",
      "type": "SELL",
      "p": 4320,
      "a": 1217
    },
    {
      "t": "13.28.05",
      "type": "SELL",
      "p": 4320,
      "a": 1606
    },
    {
      "t": "13.27.45",
      "type": "SELL",
      "p": 4320,
      "a": 1806
    },
    {
      "t": "13.27.40",
      "type": "BUY",
      "p": 4320,
      "a": 780
    },
    {
      "t": "13.27.30",
      "type": "SELL",
      "p": 4320,
      "a": 1766
    },
    {
      "t": "13.27.25",
      "type": "SELL",
      "p": 4320,
      "a": 500
    },
    {
      "t": "13.27.20",
      "type": "SELL",
      "p": 4320,
      "a": 548
    },
    {
      "t": "13.27.10",
      "type": "SELL",
      "p": 4320,
      "a": 975
    }
  ],
  "history": [
    {
      "t": "13.15.44",
      "p": 3842
    },
    {
      "t": "13.15.54",
      "p": 3842
    },
    {
      "t": "13.16.04",
      "p": 3842
    },
    {
      "t": "13.16.09",
      "p": 3918
    },
    {
      "t": "13.16.14",
      "p": 3918
    },
    {
      "t": "13.17.09",
      "p": 3918
    },
    {
      "t": "13.17.24",
      "p": 3918
    },
    {
      "t": "13.17.39",
      "p": 3918
    },
    {
      "t": "13.17.44",
      "p": 3918
    },
    {
      "t": "13.17.49",
      "p": 3918
    },
    {
      "t": "13.17.54",
      "p": 3918
    },
    {
      "t": "13.18.14",
      "p": 3918
    },
    {
      "t": "13.18.19",
      "p": 4113
    },
    {
      "t": "13.18.24",
      "p": 4113
    },
    {
      "t": "13.21.10",
      "p": 4113
    },
    {
      "t": "13.21.20",
      "p": 4113
    },
    {
      "t": "13.21.25",
      "p": 4113
    },
    {
      "t": "13.21.30",
      "p": 4113
    },
    {
      "t": "13.21.45",
      "p": 4113
    },
    {
      "t": "13.21.50",
      "p": 4113
    },
    {
      "t": "13.22.00",
      "p": 4236
    },
    {
      "t": "13.22.05",
      "p": 4236
    },
    {
      "t": "13.22.15",
      "p": 4236
    },
    {
      "t": "13.22.25",
      "p": 4236
    },
    {
      "t": "13.22.40",
      "p": 4236
    },
    {
      "t": "13.22.45",
      "p": 4236
    },
    {
      "t": "13.22.50",
      "p": 4236
    },
    {
      "t": "13.22.55",
      "p": 4236
    },
    {
      "t": "13.23.00",
      "p": 4236
    },
    {
      "t": "13.23.05",
      "p": 4236
    },
    {
      "t": "13.23.15",
      "p": 4236
    },
    {
      "t": "13.23.30",
      "p": 4236
    },
    {
      "t": "13.23.35",
      "p": 4236
    },
    {
      "t": "13.23.55",
      "p": 4236
    },
    {
      "t": "13.24.05",
      "p": 4236
    },
    {
      "t": "13.24.20",
      "p": 4236
    },
    {
      "t": "13.24.45",
      "p": 4236
    },
    {
      "t": "13.24.55",
      "p": 4236
    },
    {
      "t": "13.25.00",
      "p": 4236
    },
    {
      "t": "13.25.05",
      "p": 4236
    },
    {
      "t": "13.25.15",
      "p": 4236
    },
    {
      "t": "13.25.35",
      "p": 4236
    },
    {
      "t": "13.25.45",
      "p": 4236
    },
    {
      "t": "13.26.10",
      "p": 4236
    },
    {
      "t": "13.26.20",
      "p": 4236
    },
    {
      "t": "13.26.30",
      "p": 4236
    },
    {
      "t": "13.26.45",
      "p": 4236
    },
    {
      "t": "13.27.05",
      "p": 4320
    },
    {
      "t": "13.27.15",
      "p": 4320
    },
    {
      "t": "13.27.20",
      "p": 4320
    },
    {
      "t": "13.27.30",
      "p": 4320
    },
    {
      "t": "13.27.35",
      "p": 4320
    },
    {
      "t": "13.27.45",
      "p": 4320
    },
    {
      "t": "13.27.50",
      "p": 4320
    },
    {
      "t": "13.28.15",
      "p": 4320
    },
    {
      "t": "13.28.25",
      "p": 4320
    },
    {
      "t": "13.28.30",
      "p": 4320
    },
    {
      "t": "13.28.50",
      "p": 4320
    },
    {
      "t": "13.29.00",
      "p": 4320
    },
    {
      "t": "13.29.05",
      "p": 4320
    }
  ],
  "stats": {
    "total_investors": 1
  }
}