{
  "status": "MARKET_OPEN",
  "last_updated": 1764677669059,
  "readable_time": "2/12/2025, 12.14.29",
  "market": {
    "price": 2988,
    "trend": "📉 BEARISH (News)",
    "high": 3346,
    "low": 2629,
    "vol": 3109134,
    "mcap": 29880000000,
    "news": {
      "headline": "Inflasi global meningkat, pasar saham dunia lesu.",
      "type": "BAD",
      "timestamp": 1764677599015
    }
  },
  "leaderboard": [
    {
      "name": "Big Boss",
      "wealth": 1002993856097
    }
  ],
  "orderBook": {
    "bids": [
      {
        "p": 2982,
        "a": 5097
      },
      {
        "p": 2976,
        "a": 4410
      },
      {
        "p": 2970,
        "a": 209
      },
      {
        "p": 2964,
        "a": 737
      },
      {
        "p": 2958,
        "a": 3472
      },
      {
        "p": 2952,
        "a": 911
      },
      {
        "p": 2946,
        "a": 3927
      },
      {
        "p": 2940,
        "a": 1383
      }
    ],
    "asks": [
      {
        "p": 2993,
        "a": 3608
      },
      {
        "p": 2999,
        "a": 889
      },
      {
        "p": 3005,
        "a": 4384
      },
      {
        "p": 3011,
        "a": 1966
      },
      {
        "p": 3017,
        "a": 2800
      },
      {
        "p": 3023,
        "a": 113
      },
      {
        "p": 3029,
        "a": 3726
      },
      {
        "p": 3035,
        "a": 987
      }
    ]
  },
  "trades": [
    {
      "t": "12.14.29",
      "type": "BUY",
      "p": 2988,
      "a": 143
    },
    {
      "t": "12.14.24",
      "type": "BUY",
      "p": 2988,
      "a": 1763
    },
    {
      "t": "12.13.54",
      "type": "SELL",
      "p": 2988,
      "a": 300
    },
    {
      "t": "12.13.49",
      "type": "SELL",
      "p": 2988,
      "a": 143
    },
    {
      "t": "12.13.44",
      "type": "SELL",
      "p": 2988,
      "a": 677
    },
    {
      "t": "12.13.39",
      "type": "BUY",
      "p": 2988,
      "a": 372
    },
    {
      "t": "12.13.24",
      "type": "BUY",
      "p": 2988,
      "a": 1881
    },
    {
      "t": "12.13.19",
      "type": "BUY",
      "p": 3081,
      "a": 1683
    },
    {
      "t": "12.13.14",
      "type": "SELL",
      "p": 3081,
      "a": 105
    },
    {
      "t": "12.13.09",
      "type": "SELL",
      "p": 3081,
      "a": 1919
    },
    {
      "t": "12.13.03",
      "type": "SELL",
      "p": 3081,
      "a": 1588
    },
    {
      "t": "12.12.53",
      "type": "BUY",
      "p": 3081,
      "a": 1374
    },
    {
      "t": "12.12.48",
      "type": "SELL",
      "p": 3081,
      "a": 1143
    },
    {
      "t": "12.12.43",
      "type": "SELL",
      "p": 3081,
      "a": 1254
    },
    {
      "t": "12.12.38",
      "type": "BUY",
      "p": 3081,
      "a": 1499
    }
  ],
  "history": [
    {
      "t": "12.03.38",
      "p": 3278
    },
    {
      "t": "12.03.43",
      "p": 3278
    },
    {
      "t": "12.03.48",
      "p": 3278
    },
    {
      "t": "12.03.53",
      "p": 3278
    },
    {
      "t": "12.04.03",
      "p": 3278
    },
    {
      "t": "12.04.08",
      "p": 3278
    },
    {
      "t": "12.04.18",
      "p": 3278
    },
    {
      "t": "12.04.23",
      "p": 3278
    },
    {
      "t": "12.04.33",
      "p": 3278
    },
    {
      "t": "12.04.38",
      "p": 3278
    },
    {
      "t": "12.04.48",
      "p": 3278
    },
    {
      "t": "12.04.58",
      "p": 3278
    },
    {
      "t": "12.05.18",
      "p": 3278
    },
    {
      "t": "12.05.23",
      "p": 3278
    },
    {
      "t": "12.05.28",
      "p": 3278
    },
    {
      "t": "12.05.33",
      "p": 3278
    },
    {
      "t": "12.05.38",
      "p": 3278
    },
    {
      "t": "12.05.48",
      "p": 3278
    },
    {
      "t": "12.05.58",
      "p": 3278
    },
    {
      "t": "12.06.23",
      "p": 3278
    },
    {
      "t": "12.06.28",
      "p": 3278
    },
    {
      "t": "12.06.38",
      "p": 3278
    },
    {
      "t": "12.06.43",
      "p": 3278
    },
    {
      "t": "12.06.58",
      "p": 3278
    },
    {
      "t": "12.07.13",
      "p": 3278
    },
    {
      "t": "12.07.18",
      "p": 3278
    },
    {
      "t": "12.07.23",
      "p": 3081
    },
    {
      "t": "12.07.33",
      "p": 3081
    },
    {
      "t": "12.07.38",
      "p": 3081
    },
    {
      "t": "12.07.53",
      "p": 3081
    },
    {
      "t": "12.07.58",
      "p": 3081
    },
    {
      "t": "12.08.18",
      "p": 3081
    },
    {
      "t": "12.08.33",
      "p": 3081
    },
    {
      "t": "12.08.43",
      "p": 3081
    },
    {
      "t": "12.09.03",
      "p": 3081
    },
    {
      "t": "12.09.18",
      "p": 3081
    },
    {
      "t": "12.09.23",
      "p": 3081
    },
    {
      "t": "12.09.58",
      "p": 3081
    },
    {
      "t": "12.10.13",
      "p": 3081
    },
    {
      "t": "12.10.23",
      "p": 3081
    },
    {
      "t": "12.10.33",
      "p": 3081
    },
    {
      "t": "12.10.48",
      "p": 3081
    },
    {
      "t": "12.10.53",
      "p": 3081
    },
    {
      "t": "12.10.58",
      "p": 3081
    },
    {
      "t": "12.11.03",
      "p": 3081
    },
    {
      "t": "12.11.13",
      "p": 3081
    },
    {
      "t": "12.11.23",
      "p": 3081
    },
    {
      "t": "12.11.28",
      "p": 3081
    },
    {
      "t": "12.11.43",
      "p": 3081
    },
    {
      "t": "12.12.48",
      "p": 3081
    },
    {
      "t": "12.13.09",
      "p": 3081
    },
    {
      "t": "12.13.14",
      "p": 3081
    },
    {
      "t": "12.13.24",
      "p": 2988
    },
    {
      "t": "12.13.29",
      "p": 2988
    },
    {
      "t": "12.13.44",
      "p": 2988
    },
    {
      "t": "12.13.54",
      "p": 2988
    },
    {
      "t": "12.13.59",
      "p": 2988
    },
    {
      "t": "12.14.14",
      "p": 2988
    },
    {
      "t": "12.14.19",
      "p": 2988
    },
    {
      "t": "12.14.29",
      "p": 2988
    }
  ],
  "stats": {
    "total_investors": 1
  }
}