{
  "status": "ONLINE",
  "last_updated": 1764178218666,
  "market": {
    "price": 779,
    "trend": "📉 TURUN",
    "high": 817,
    "low": 740,
    "vol": 24121
  },
  "orderBook": {
    "bids": [
      {
        "p": 778,
        "a": 666
      },
      {
        "p": 777,
        "a": 547
      },
      {
        "p": 776,
        "a": 765
      },
      {
        "p": 775,
        "a": 153
      },
      {
        "p": 775,
        "a": 376
      }
    ],
    "asks": [
      {
        "p": 779,
        "a": 578
      },
      {
        "p": 780,
        "a": 355
      },
      {
        "p": 781,
        "a": 40
      },
      {
        "p": 782,
        "a": 568
      },
      {
        "p": 782,
        "a": 402
      }
    ]
  },
  "trades": [
    {
      "t": "17.30.18",
      "type": "BUY",
      "p": 779,
      "a": 131
    },
    {
      "t": "17.30.03",
      "type": "BUY",
      "p": 779,
      "a": 122
    },
    {
      "t": "17.29.53",
      "type": "BUY",
      "p": 779,
      "a": 445
    },
    {
      "t": "17.29.43",
      "type": "BUY",
      "p": 779,
      "a": 350
    },
    {
      "t": "17.29.38",
      "type": "SELL",
      "p": 779,
      "a": 197
    },
    {
      "t": "17.29.28",
      "type": "BUY",
      "p": 779,
      "a": 225
    },
    {
      "t": "17.29.23",
      "type": "SELL",
      "p": 779,
      "a": 205
    },
    {
      "t": "17.29.18",
      "type": "SELL",
      "p": 779,
      "a": 375
    },
    {
      "t": "17.29.13",
      "type": "SELL",
      "p": 779,
      "a": 103
    },
    {
      "t": "17.29.08",
      "type": "SELL",
      "p": 779,
      "a": 377
    }
  ],
  "history": [
    {
      "t": "17.15.48",
      "p": 779
    },
    {
      "t": "17.16.03",
      "p": 779
    },
    {
      "t": "17.16.38",
      "p": 779
    },
    {
      "t": "17.16.48",
      "p": 779
    },
    {
      "t": "17.16.58",
      "p": 779
    },
    {
      "t": "17.17.23",
      "p": 779
    },
    {
      "t": "17.17.33",
      "p": 779
    },
    {
      "t": "17.17.53",
      "p": 779
    },
    {
      "t": "17.18.03",
      "p": 779
    },
    {
      "t": "17.18.28",
      "p": 779
    },
    {
      "t": "17.18.48",
      "p": 779
    },
    {
      "t": "17.19.13",
      "p": 779
    },
    {
      "t": "17.19.33",
      "p": 779
    },
    {
      "t": "17.20.13",
      "p": 779
    },
    {
      "t": "17.20.18",
      "p": 779
    },
    {
      "t": "17.20.43",
      "p": 779
    },
    {
      "t": "17.20.48",
      "p": 779
    },
    {
      "t": "17.20.58",
      "p": 779
    },
    {
      "t": "17.21.03",
      "p": 779
    },
    {
      "t": "17.21.53",
      "p": 779
    },
    {
      "t": "17.22.08",
      "p": 779
    },
    {
      "t": "17.22.13",
      "p": 779
    },
    {
      "t": "17.22.18",
      "p": 779
    },
    {
      "t": "17.22.43",
      "p": 779
    },
    {
      "t": "17.22.48",
      "p": 779
    },
    {
      "t": "17.22.53",
      "p": 779
    },
    {
      "t": "17.22.58",
      "p": 779
    },
    {
      "t": "17.23.38",
      "p": 779
    },
    {
      "t": "17.23.53",
      "p": 779
    },
    {
      "t": "17.24.03",
      "p": 779
    },
    {
      "t": "17.24.13",
      "p": 779
    },
    {
      "t": "17.25.08",
      "p": 779
    },
    {
      "t": "17.25.53",
      "p": 779
    },
    {
      "t": "17.26.08",
      "p": 779
    },
    {
      "t": "17.26.13",
      "p": 779
    },
    {
      "t": "17.26.18",
      "p": 779
    },
    {
      "t": "17.26.23",
      "p": 779
    },
    {
      "t": "17.26.38",
      "p": 779
    },
    {
      "t": "17.26.53",
      "p": 779
    },
    {
      "t": "17.27.13",
      "p": 779
    },
    {
      "t": "17.27.18",
      "p": 779
    },
    {
      "t": "17.27.33",
      "p": 779
    },
    {
      "t": "17.27.48",
      "p": 779
    },
    {
      "t": "17.28.13",
      "p": 779
    },
    {
      "t": "17.28.33",
      "p": 779
    },
    {
      "t": "17.28.38",
      "p": 779
    },
    {
      "t": "17.28.48",
      "p": 779
    },
    {
      "t": "17.29.13",
      "p": 779
    },
    {
      "t": "17.29.43",
      "p": 779
    },
    {
      "t": "17.30.03",
      "p": 779
    }
  ],
  "stats": {
    "total_investors": 1
  }
}