{
  "status": "MARKET_OPEN",
  "last_updated": 1764500780056,
  "readable_time": "30/11/2025, 11.06.20",
  "market": {
    "price": 1180,
    "trend": "📈 BULLISH (News)",
    "high": 1321,
    "low": 1038,
    "vol": 2599753,
    "mcap": 11800000000,
    "news": {
      "headline": "Boss $ARA mengumumkan partnership strategis dengan Google Cloud!",
      "type": "GOOD",
      "timestamp": 1764500224434
    }
  },
  "leaderboard": [
    {
      "name": "Big Boss",
      "wealth": 1001179999999
    }
  ],
  "orderBook": {
    "bids": [
      {
        "p": 1177,
        "a": 2628
      },
      {
        "p": 1175,
        "a": 4923
      },
      {
        "p": 1172,
        "a": 3256
      },
      {
        "p": 1170,
        "a": 4603
      },
      {
        "p": 1168,
        "a": 2360
      },
      {
        "p": 1165,
        "a": 4820
      },
      {
        "p": 1163,
        "a": 2415
      },
      {
        "p": 1161,
        "a": 707
      }
    ],
    "asks": [
      {
        "p": 1182,
        "a": 423
      },
      {
        "p": 1184,
        "a": 4867
      },
      {
        "p": 1187,
        "a": 4419
      },
      {
        "p": 1189,
        "a": 3172
      },
      {
        "p": 1191,
        "a": 183
      },
      {
        "p": 1194,
        "a": 1589
      },
      {
        "p": 1196,
        "a": 2389
      },
      {
        "p": 1198,
        "a": 3628
      }
    ]
  },
  "trades": [
    {
      "t": "11.06.20",
      "type": "BUY",
      "p": 1180,
      "a": 445
    },
    {
      "t": "11.06.15",
      "type": "SELL",
      "p": 1180,
      "a": 1722
    },
    {
      "t": "11.06.10",
      "type": "BUY",
      "p": 1180,
      "a": 1549
    },
    {
      "t": "11.06.05",
      "type": "BUY",
      "p": 1180,
      "a": 1510
    },
    {
      "t": "11.06.00",
      "type": "SELL",
      "p": 1180,
      "a": 712
    },
    {
      "t": "11.05.55",
      "type": "BUY",
      "p": 1180,
      "a": 1398
    },
    {
      "t": "11.05.50",
      "type": "BUY",
      "p": 1180,
      "a": 1671
    },
    {
      "t": "11.05.35",
      "type": "SELL",
      "p": 1180,
      "a": 754
    },
    {
      "t": "11.05.30",
      "type": "SELL",
      "p": 1180,
      "a": 576
    },
    {
      "t": "11.05.25",
      "type": "SELL",
      "p": 1180,
      "a": 785
    },
    {
      "t": "11.05.15",
      "type": "SELL",
      "p": 1180,
      "a": 1779
    },
    {
      "t": "11.05.05",
      "type": "BUY",
      "p": 1180,
      "a": 1194
    },
    {
      "t": "11.05.00",
      "type": "SELL",
      "p": 1180,
      "a": 629
    },
    {
      "t": "11.04.50",
      "type": "SELL",
      "p": 1180,
      "a": 777
    },
    {
      "t": "11.04.35",
      "type": "BUY",
      "p": 1180,
      "a": 444
    }
  ],
  "history": [
    {
      "t": "10.52.35",
      "p": 1061
    },
    {
      "t": "10.52.45",
      "p": 1061
    },
    {
      "t": "10.52.55",
      "p": 1061
    },
    {
      "t": "10.53.05",
      "p": 1124
    },
    {
      "t": "10.53.10",
      "p": 1124
    },
    {
      "t": "10.53.20",
      "p": 1124
    },
    {
      "t": "10.53.25",
      "p": 1124
    },
    {
      "t": "10.53.55",
      "p": 1124
    },
    {
      "t": "10.54.10",
      "p": 1124
    },
    {
      "t": "10.54.30",
      "p": 1124
    },
    {
      "t": "10.55.09",
      "p": 1124
    },
    {
      "t": "10.55.19",
      "p": 1124
    },
    {
      "t": "10.55.24",
      "p": 1124
    },
    {
      "t": "10.55.44",
      "p": 1124
    },
    {
      "t": "10.55.59",
      "p": 1124
    },
    {
      "t": "10.56.09",
      "p": 1124
    },
    {
      "t": "10.56.29",
      "p": 1124
    },
    {
      "t": "10.56.49",
      "p": 1124
    },
    {
      "t": "10.57.04",
      "p": 1124
    },
    {
      "t": "10.57.09",
      "p": 1180
    },
    {
      "t": "10.57.29",
      "p": 1180
    },
    {
      "t": "10.57.34",
      "p": 1180
    },
    {
      "t": "10.57.44",
      "p": 1180
    },
    {
      "t": "10.57.54",
      "p": 1180
    },
    {
      "t": "10.58.14",
      "p": 1180
    },
    {
      "t": "10.58.24",
      "p": 1180
    },
    {
      "t": "10.58.29",
      "p": 1180
    },
    {
      "t": "10.58.34",
      "p": 1180
    },
    {
      "t": "10.58.39",
      "p": 1180
    },
    {
      "t": "10.58.54",
      "p": 1180
    },
    {
      "t": "10.59.09",
      "p": 1180
    },
    {
      "t": "10.59.14",
      "p": 1180
    },
    {
      "t": "10.59.44",
      "p": 1180
    },
    {
      "t": "10.59.59",
      "p": 1180
    },
    {
      "t": "11.00.04",
      "p": 1180
    },
    {
      "t": "11.00.09",
      "p": 1180
    },
    {
      "t": "11.00.24",
      "p": 1180
    },
    {
      "t": "11.00.49",
      "p": 1180
    },
    {
      "t": "11.00.54",
      "p": 1180
    },
    {
      "t": "11.00.59",
      "p": 1180
    },
    {
      "t": "11.01.09",
      "p": 1180
    },
    {
      "t": "11.01.14",
      "p": 1180
    },
    {
      "t": "11.01.19",
      "p": 1180
    },
    {
      "t": "11.01.29",
      "p": 1180
    },
    {
      "t": "11.01.59",
      "p": 1180
    },
    {
      "t": "11.02.44",
      "p": 1180
    },
    {
      "t": "11.02.49",
      "p": 1180
    },
    {
      "t": "11.02.54",
      "p": 1180
    },
    {
      "t": "11.04.25",
      "p": 1180
    },
    {
      "t": "11.04.30",
      "p": 1180
    },
    {
      "t": "11.04.50",
      "p": 1180
    },
    {
      "t": "11.04.55",
      "p": 1180
    },
    {
      "t": "11.05.10",
      "p": 1180
    },
    {
      "t": "11.05.20",
      "p": 1180
    },
    {
      "t": "11.05.35",
      "p": 1180
    },
    {
      "t": "11.05.40",
      "p": 1180
    },
    {
      "t": "11.05.50",
      "p": 1180
    },
    {
      "t": "11.05.55",
      "p": 1180
    },
    {
      "t": "11.06.15",
      "p": 1180
    },
    {
      "t": "11.06.20",
      "p": 1180
    }
  ],
  "stats": {
    "total_investors": 2
  }
}