{
  "status": "ONLINE",
  "last_updated": 1764167860259,
  "market": {
    "price": 752,
    "trend": "📈 NAIK",
    "supply": 100000
  },
  "stats": {
    "total_investors": 1
  },
  "history": [
    {
      "t": "14.34.30",
      "p": 693
    },
    {
      "t": "14.34.40",
      "p": 693
    },
    {
      "t": "14.34.50",
      "p": 693
    },
    {
      "t": "14.35.00",
      "p": 716
    },
    {
      "t": "14.35.10",
      "p": 719
    },
    {
      "t": "14.35.20",
      "p": 742
    },
    {
      "t": "14.35.30",
      "p": 742
    },
    {
      "t": "14.35.40",
      "p": 742
    },
    {
      "t": "14.35.50",
      "p": 742
    },
    {
      "t": "14.36.00",
      "p": 742
    },
    {
      "t": "14.36.10",
      "p": 742
    },
    {
      "t": "14.36.20",
      "p": 742
    },
    {
      "t": "14.36.30",
      "p": 742
    },
    {
      "t": "14.36.40",
      "p": 742
    },
    {
      "t": "14.36.50",
      "p": 742
    },
    {
      "t": "14.37.00",
      "p": 742
    },
    {
      "t": "14.37.10",
      "p": 752
    },
    {
      "t": "14.37.20",
      "p": 752
    },
    {
      "t": "14.37.30",
      "p": 752
    },
    {
      "t": "14.37.40",
      "p": 752
    }
  ]
}