{
  "status": "MARKET_OPEN",
  "last_updated": 1764680724828,
  "readable_time": "2/12/2025, 13.05.24",
  "market": {
    "price": 3969,
    "trend": "📈 BULLISH (News)",
    "high": 4445,
    "low": 3492,
    "vol": 5731441,
    "mcap": 39690000000,
    "news": {
      "headline": "Rumor: Token $ARA akan listing di exchange Tier-1 bulan depan.",
      "type": "GOOD",
      "timestamp": 1764680414598
    }
  },
  "leaderboard": [
    {
      "name": "Big Boss",
      "wealth": 1003979771888
    }
  ],
  "orderBook": {
    "bids": [
      {
        "p": 3961,
        "a": 1567
      },
      {
        "p": 3953,
        "a": 1644
      },
      {
        "p": 3945,
        "a": 470
      },
      {
        "p": 3937,
        "a": 4736
      },
      {
        "p": 3929,
        "a": 4096
      },
      {
        "p": 3921,
        "a": 4941
      },
      {
        "p": 3913,
        "a": 2562
      },
      {
        "p": 3905,
        "a": 318
      }
    ],
    "asks": [
      {
        "p": 3976,
        "a": 4219
      },
      {
        "p": 3984,
        "a": 532
      },
      {
        "p": 3992,
        "a": 3491
      },
      {
        "p": 4000,
        "a": 3550
      },
      {
        "p": 4008,
        "a": 2268
      },
      {
        "p": 4016,
        "a": 4522
      },
      {
        "p": 4024,
        "a": 2092
      },
      {
        "p": 4032,
        "a": 4513
      }
    ]
  },
  "trades": [
    {
      "t": "13.05.24",
      "type": "BUY",
      "p": 3969,
      "a": 1593
    },
    {
      "t": "13.05.19",
      "type": "BUY",
      "p": 3969,
      "a": 269
    },
    {
      "t": "13.05.14",
      "type": "BUY",
      "p": 3969,
      "a": 814
    },
    {
      "t": "13.05.09",
      "type": "BUY",
      "p": 3969,
      "a": 964
    },
    {
      "t": "13.05.04",
      "type": "SELL",
      "p": 3969,
      "a": 1928
    },
    {
      "t": "13.04.59",
      "type": "BUY",
      "p": 3969,
      "a": 1426
    },
    {
      "t": "13.04.49",
      "type": "SELL",
      "p": 3969,
      "a": 289
    },
    {
      "t": "13.04.44",
      "type": "SELL",
      "p": 3969,
      "a": 31
    },
    {
      "t": "13.04.24",
      "type": "SELL",
      "p": 3969,
      "a": 1455
    },
    {
      "t": "13.04.19",
      "type": "BUY",
      "p": 3969,
      "a": 1154
    },
    {
      "t": "13.04.09",
      "type": "SELL",
      "p": 3969,
      "a": 277
    },
    {
      "t": "13.04.04",
      "type": "SELL",
      "p": 3969,
      "a": 258
    },
    {
      "t": "13.03.59",
      "type": "SELL",
      "p": 3969,
      "a": 1862
    },
    {
      "t": "13.03.54",
      "type": "SELL",
      "p": 3969,
      "a": 322
    },
    {
      "t": "13.03.49",
      "type": "BUY",
      "p": 3969,
      "a": 1632
    }
  ],
  "history": [
    {
      "t": "12.52.29",
      "p": 3636
    },
    {
      "t": "12.52.34",
      "p": 3636
    },
    {
      "t": "12.52.44",
      "p": 3745
    },
    {
      "t": "12.52.59",
      "p": 3745
    },
    {
      "t": "12.53.09",
      "p": 3745
    },
    {
      "t": "12.53.19",
      "p": 3745
    },
    {
      "t": "12.53.34",
      "p": 3745
    },
    {
      "t": "12.53.39",
      "p": 3745
    },
    {
      "t": "12.53.49",
      "p": 3745
    },
    {
      "t": "12.53.54",
      "p": 3745
    },
    {
      "t": "12.53.59",
      "p": 3745
    },
    {
      "t": "12.54.19",
      "p": 3745
    },
    {
      "t": "12.54.24",
      "p": 3745
    },
    {
      "t": "12.54.49",
      "p": 3745
    },
    {
      "t": "12.54.54",
      "p": 3745
    },
    {
      "t": "12.55.04",
      "p": 3745
    },
    {
      "t": "12.55.09",
      "p": 3745
    },
    {
      "t": "12.55.24",
      "p": 3745
    },
    {
      "t": "12.55.29",
      "p": 3745
    },
    {
      "t": "12.55.34",
      "p": 3745
    },
    {
      "t": "12.55.44",
      "p": 3745
    },
    {
      "t": "12.55.54",
      "p": 3745
    },
    {
      "t": "12.56.04",
      "p": 3745
    },
    {
      "t": "12.56.09",
      "p": 3745
    },
    {
      "t": "12.57.09",
      "p": 3745
    },
    {
      "t": "12.57.14",
      "p": 3745
    },
    {
      "t": "12.57.29",
      "p": 3745
    },
    {
      "t": "12.57.54",
      "p": 3745
    },
    {
      "t": "12.58.14",
      "p": 3745
    },
    {
      "t": "12.58.29",
      "p": 3745
    },
    {
      "t": "12.58.34",
      "p": 3745
    },
    {
      "t": "12.58.59",
      "p": 3745
    },
    {
      "t": "12.59.14",
      "p": 3745
    },
    {
      "t": "12.59.19",
      "p": 3745
    },
    {
      "t": "12.59.29",
      "p": 3745
    },
    {
      "t": "12.59.34",
      "p": 3745
    },
    {
      "t": "12.59.49",
      "p": 3745
    },
    {
      "t": "12.59.54",
      "p": 3745
    },
    {
      "t": "13.00.04",
      "p": 3745
    },
    {
      "t": "13.00.14",
      "p": 3745
    },
    {
      "t": "13.00.19",
      "p": 3969
    },
    {
      "t": "13.00.29",
      "p": 3969
    },
    {
      "t": "13.00.49",
      "p": 3969
    },
    {
      "t": "13.00.59",
      "p": 3969
    },
    {
      "t": "13.01.04",
      "p": 3969
    },
    {
      "t": "13.01.24",
      "p": 3969
    },
    {
      "t": "13.01.29",
      "p": 3969
    },
    {
      "t": "13.01.34",
      "p": 3969
    },
    {
      "t": "13.02.09",
      "p": 3969
    },
    {
      "t": "13.02.19",
      "p": 3969
    },
    {
      "t": "13.02.24",
      "p": 3969
    },
    {
      "t": "13.02.39",
      "p": 3969
    },
    {
      "t": "13.02.44",
      "p": 3969
    },
    {
      "t": "13.03.19",
      "p": 3969
    },
    {
      "t": "13.03.29",
      "p": 3969
    },
    {
      "t": "13.04.04",
      "p": 3969
    },
    {
      "t": "13.04.14",
      "p": 3969
    },
    {
      "t": "13.04.49",
      "p": 3969
    },
    {
      "t": "13.05.14",
      "p": 3969
    },
    {
      "t": "13.05.24",
      "p": 3969
    }
  ],
  "stats": {
    "total_investors": 1
  }
}