{
  "status": "MARKET_OPEN",
  "last_updated": 1764673280334,
  "readable_time": "2/12/2025, 11.01.20",
  "market": {
    "price": 2966,
    "trend": "📉 BEARISH (News)",
    "high": 3321,
    "low": 2610,
    "vol": 4266097,
    "mcap": 29660000000,
    "news": {
      "headline": "Aksi jual massal (Panic Selling) terdeteksi di zona Asia.",
      "type": "BAD",
      "timestamp": 1764670305525
    }
  },
  "leaderboard": [
    {
      "name": "Big Boss",
      "wealth": 1002971745855
    }
  ],
  "orderBook": {
    "bids": [
      {
        "p": 2960,
        "a": 1430
      },
      {
        "p": 2954,
        "a": 2060
      },
      {
        "p": 2948,
        "a": 4394
      },
      {
        "p": 2942,
        "a": 936
      },
      {
        "p": 2936,
        "a": 2202
      },
      {
        "p": 2930,
        "a": 727
      },
      {
        "p": 2924,
        "a": 3399
      },
      {
        "p": 2918,
        "a": 2312
      }
    ],
    "asks": [
      {
        "p": 2971,
        "a": 2915
      },
      {
        "p": 2977,
        "a": 1405
      },
      {
        "p": 2983,
        "a": 4595
      },
      {
        "p": 2989,
        "a": 4776
      },
      {
        "p": 2995,
        "a": 2044
      },
      {
        "p": 3001,
        "a": 3731
      },
      {
        "p": 3007,
        "a": 3273
      },
      {
        "p": 3013,
        "a": 5080
      }
    ]
  },
  "trades": [
    {
      "t": "11.01.20",
      "type": "SELL",
      "p": 2966,
      "a": 915
    },
    {
      "t": "11.01.15",
      "type": "BUY",
      "p": 2966,
      "a": 899
    },
    {
      "t": "11.01.10",
      "type": "SELL",
      "p": 2966,
      "a": 822
    },
    {
      "t": "11.01.05",
      "type": "SELL",
      "p": 2966,
      "a": 69
    },
    {
      "t": "11.01.00",
      "type": "BUY",
      "p": 2966,
      "a": 694
    },
    {
      "t": "11.00.55",
      "type": "SELL",
      "p": 2966,
      "a": 385
    },
    {
      "t": "11.00.50",
      "type": "BUY",
      "p": 2966,
      "a": 109
    },
    {
      "t": "11.00.35",
      "type": "SELL",
      "p": 2966,
      "a": 164
    },
    {
      "t": "11.00.20",
      "type": "BUY",
      "p": 2966,
      "a": 400
    },
    {
      "t": "11.00.00",
      "type": "SELL",
      "p": 2966,
      "a": 1206
    },
    {
      "t": "10.59.55",
      "type": "BUY",
      "p": 2966,
      "a": 456
    },
    {
      "t": "10.59.50",
      "type": "BUY",
      "p": 2966,
      "a": 1129
    },
    {
      "t": "10.59.30",
      "type": "SELL",
      "p": 2966,
      "a": 744
    },
    {
      "t": "10.59.25",
      "type": "BUY",
      "p": 2966,
      "a": 1575
    },
    {
      "t": "10.59.20",
      "type": "SELL",
      "p": 2966,
      "a": 1544
    }
  ],
  "history": [
    {
      "t": "10.03.25",
      "p": 2926
    },
    {
      "t": "10.03.30",
      "p": 2926
    },
    {
      "t": "10.03.35",
      "p": 2926
    },
    {
      "t": "10.04.30",
      "p": 2926
    },
    {
      "t": "10.04.35",
      "p": 2926
    },
    {
      "t": "10.04.40",
      "p": 2926
    },
    {
      "t": "10.04.50",
      "p": 3043
    },
    {
      "t": "10.04.55",
      "p": 3043
    },
    {
      "t": "10.05.05",
      "p": 3043
    },
    {
      "t": "10.05.40",
      "p": 3043
    },
    {
      "t": "10.06.05",
      "p": 3043
    },
    {
      "t": "10.06.20",
      "p": 3043
    },
    {
      "t": "10.06.35",
      "p": 3043
    },
    {
      "t": "10.06.40",
      "p": 3043
    },
    {
      "t": "10.06.50",
      "p": 3043
    },
    {
      "t": "10.07.10",
      "p": 3043
    },
    {
      "t": "10.07.20",
      "p": 3043
    },
    {
      "t": "10.07.25",
      "p": 3043
    },
    {
      "t": "10.07.40",
      "p": 3043
    },
    {
      "t": "10.07.45",
      "p": 3043
    },
    {
      "t": "10.08.15",
      "p": 3043
    },
    {
      "t": "10.08.20",
      "p": 3043
    },
    {
      "t": "10.08.25",
      "p": 3043
    },
    {
      "t": "10.08.30",
      "p": 3043
    },
    {
      "t": "10.08.40",
      "p": 3043
    },
    {
      "t": "10.08.45",
      "p": 3043
    },
    {
      "t": "10.09.20",
      "p": 3043
    },
    {
      "t": "10.09.40",
      "p": 3043
    },
    {
      "t": "10.09.45",
      "p": 3195
    },
    {
      "t": "10.10.00",
      "p": 3195
    },
    {
      "t": "10.10.10",
      "p": 3195
    },
    {
      "t": "10.10.20",
      "p": 3195
    },
    {
      "t": "10.10.30",
      "p": 3195
    },
    {
      "t": "10.10.50",
      "p": 3195
    },
    {
      "t": "10.11.00",
      "p": 3195
    },
    {
      "t": "10.11.10",
      "p": 3035
    },
    {
      "t": "10.11.25",
      "p": 3156
    },
    {
      "t": "10.11.30",
      "p": 3156
    },
    {
      "t": "10.11.45",
      "p": 3156
    },
    {
      "t": "10.11.50",
      "p": 2966
    },
    {
      "t": "10.12.00",
      "p": 2966
    },
    {
      "t": "10.12.05",
      "p": 2966
    },
    {
      "t": "10.58.20",
      "p": 2966
    },
    {
      "t": "10.58.35",
      "p": 2966
    },
    {
      "t": "10.58.40",
      "p": 2966
    },
    {
      "t": "10.58.55",
      "p": 2966
    },
    {
      "t": "10.59.05",
      "p": 2966
    },
    {
      "t": "10.59.25",
      "p": 2966
    },
    {
      "t": "10.59.30",
      "p": 2966
    },
    {
      "t": "10.59.40",
      "p": 2966
    },
    {
      "t": "10.59.45",
      "p": 2966
    },
    {
      "t": "10.59.50",
      "p": 2966
    },
    {
      "t": "10.59.55",
      "p": 2966
    },
    {
      "t": "11.00.05",
      "p": 2966
    },
    {
      "t": "11.00.25",
      "p": 2966
    },
    {
      "t": "11.00.35",
      "p": 2966
    },
    {
      "t": "11.00.50",
      "p": 2966
    },
    {
      "t": "11.00.55",
      "p": 2966
    },
    {
      "t": "11.01.15",
      "p": 2966
    },
    {
      "t": "11.01.20",
      "p": 2966
    }
  ],
  "stats": {
    "total_investors": 1
  }
}