{
  "status": "MARKET_OPEN",
  "last_updated": 1764505824721,
  "readable_time": "30/11/2025, 12.30.24",
  "market": {
    "price": 1157,
    "trend": "📈 BULLISH (News)",
    "high": 1295,
    "low": 1018,
    "vol": 4052547,
    "mcap": 11570000000,
    "news": {
      "headline": "Komunitas $ARA mencapai rekor 10.000 member aktif di Telegram.",
      "type": "GOOD",
      "timestamp": 1764505619598
    }
  },
  "leaderboard": [
    {
      "name": "Big Boss",
      "wealth": 1001156999999
    },
    {
      "name": "Investor",
      "wealth": 150000
    }
  ],
  "orderBook": {
    "bids": [
      {
        "p": 1154,
        "a": 499
      },
      {
        "p": 1152,
        "a": 188
      },
      {
        "p": 1150,
        "a": 1675
      },
      {
        "p": 1147,
        "a": 4529
      },
      {
        "p": 1145,
        "a": 2213
      },
      {
        "p": 1143,
        "a": 3538
      },
      {
        "p": 1140,
        "a": 3867
      },
      {
        "p": 1138,
        "a": 2893
      }
    ],
    "asks": [
      {
        "p": 1159,
        "a": 3811
      },
      {
        "p": 1161,
        "a": 4241
      },
      {
        "p": 1163,
        "a": 3411
      },
      {
        "p": 1166,
        "a": 1243
      },
      {
        "p": 1168,
        "a": 924
      },
      {
        "p": 1170,
        "a": 3422
      },
      {
        "p": 1173,
        "a": 3647
      },
      {
        "p": 1175,
        "a": 2020
      }
    ]
  },
  "trades": [
    {
      "t": "12.30.24",
      "type": "SELL",
      "p": 1157,
      "a": 1288
    },
    {
      "t": "12.30.19",
      "type": "BUY",
      "p": 1157,
      "a": 1456
    },
    {
      "t": "12.30.14",
      "type": "BUY",
      "p": 1157,
      "a": 1207
    },
    {
      "t": "12.30.04",
      "type": "SELL",
      "p": 1157,
      "a": 1261
    },
    {
      "t": "12.29.59",
      "type": "BUY",
      "p": 1157,
      "a": 880
    },
    {
      "t": "12.29.54",
      "type": "SELL",
      "p": 1157,
      "a": 1055
    },
    {
      "t": "12.29.49",
      "type": "BUY",
      "p": 1157,
      "a": 1502
    },
    {
      "t": "12.29.39",
      "type": "BUY",
      "p": 1157,
      "a": 1770
    },
    {
      "t": "12.29.34",
      "type": "SELL",
      "p": 1157,
      "a": 1969
    },
    {
      "t": "12.29.24",
      "type": "BUY",
      "p": 1157,
      "a": 1116
    },
    {
      "t": "12.29.19",
      "type": "SELL",
      "p": 1157,
      "a": 1673
    },
    {
      "t": "12.29.09",
      "type": "SELL",
      "p": 1157,
      "a": 858
    },
    {
      "t": "12.29.04",
      "type": "SELL",
      "p": 1157,
      "a": 1270
    },
    {
      "t": "12.28.59",
      "type": "SELL",
      "p": 1157,
      "a": 302
    },
    {
      "t": "12.28.54",
      "type": "BUY",
      "p": 1157,
      "a": 1350
    }
  ],
  "history": [
    {
      "t": "12.19.40",
      "p": 1113
    },
    {
      "t": "12.19.55",
      "p": 1113
    },
    {
      "t": "12.20.05",
      "p": 1113
    },
    {
      "t": "12.20.10",
      "p": 1113
    },
    {
      "t": "12.20.15",
      "p": 1113
    },
    {
      "t": "12.20.30",
      "p": 1113
    },
    {
      "t": "12.20.50",
      "p": 1113
    },
    {
      "t": "12.21.15",
      "p": 1113
    },
    {
      "t": "12.21.20",
      "p": 1113
    },
    {
      "t": "12.21.25",
      "p": 1113
    },
    {
      "t": "12.21.35",
      "p": 1113
    },
    {
      "t": "12.21.45",
      "p": 1113
    },
    {
      "t": "12.21.50",
      "p": 1113
    },
    {
      "t": "12.22.00",
      "p": 1113
    },
    {
      "t": "12.22.05",
      "p": 1113
    },
    {
      "t": "12.22.15",
      "p": 1113
    },
    {
      "t": "12.22.24",
      "p": 1113
    },
    {
      "t": "12.22.34",
      "p": 1113
    },
    {
      "t": "12.22.54",
      "p": 1113
    },
    {
      "t": "12.22.59",
      "p": 1113
    },
    {
      "t": "12.23.04",
      "p": 1113
    },
    {
      "t": "12.23.24",
      "p": 1113
    },
    {
      "t": "12.23.39",
      "p": 1113
    },
    {
      "t": "12.23.49",
      "p": 1113
    },
    {
      "t": "12.23.54",
      "p": 1146
    },
    {
      "t": "12.24.09",
      "p": 1146
    },
    {
      "t": "12.24.39",
      "p": 1146
    },
    {
      "t": "12.24.44",
      "p": 1146
    },
    {
      "t": "12.24.54",
      "p": 1146
    },
    {
      "t": "12.25.39",
      "p": 1146
    },
    {
      "t": "12.25.49",
      "p": 1146
    },
    {
      "t": "12.25.54",
      "p": 1146
    },
    {
      "t": "12.26.04",
      "p": 1146
    },
    {
      "t": "12.26.24",
      "p": 1146
    },
    {
      "t": "12.26.29",
      "p": 1146
    },
    {
      "t": "12.26.34",
      "p": 1146
    },
    {
      "t": "12.26.39",
      "p": 1146
    },
    {
      "t": "12.26.49",
      "p": 1146
    },
    {
      "t": "12.26.54",
      "p": 1146
    },
    {
      "t": "12.27.04",
      "p": 1157
    },
    {
      "t": "12.27.24",
      "p": 1157
    },
    {
      "t": "12.27.29",
      "p": 1157
    },
    {
      "t": "12.27.39",
      "p": 1157
    },
    {
      "t": "12.27.54",
      "p": 1157
    },
    {
      "t": "12.28.04",
      "p": 1157
    },
    {
      "t": "12.28.09",
      "p": 1157
    },
    {
      "t": "12.28.29",
      "p": 1157
    },
    {
      "t": "12.28.34",
      "p": 1157
    },
    {
      "t": "12.28.39",
      "p": 1157
    },
    {
      "t": "12.28.54",
      "p": 1157
    },
    {
      "t": "12.28.59",
      "p": 1157
    },
    {
      "t": "12.29.09",
      "p": 1157
    },
    {
      "t": "12.29.34",
      "p": 1157
    },
    {
      "t": "12.29.44",
      "p": 1157
    },
    {
      "t": "12.29.49",
      "p": 1157
    },
    {
      "t": "12.29.54",
      "p": 1157
    },
    {
      "t": "12.29.59",
      "p": 1157
    },
    {
      "t": "12.30.04",
      "p": 1157
    },
    {
      "t": "12.30.09",
      "p": 1157
    },
    {
      "t": "12.30.19",
      "p": 1157
    }
  ],
  "stats": {
    "total_investors": 3
  }
}