{
  "status": "MARKET_OPEN",
  "last_updated": 1764653020566,
  "readable_time": "2/12/2025, 05.23.40",
  "market": {
    "price": 1665,
    "trend": "📈 BULLISH (News)",
    "high": 1864,
    "low": 1465,
    "vol": 1289821,
    "mcap": 16650000000,
    "news": {
      "headline": "Boss $ARA mengumumkan partnership strategis dengan Google Cloud!",
      "type": "GOOD",
      "timestamp": 1764652144985
    }
  },
  "leaderboard": [
    {
      "name": "Big Boss",
      "wealth": 1001664226544
    }
  ],
  "orderBook": {
    "bids": [
      {
        "p": 1661,
        "a": 1065
      },
      {
        "p": 1658,
        "a": 3387
      },
      {
        "p": 1655,
        "a": 3488
      },
      {
        "p": 1651,
        "a": 2611
      },
      {
        "p": 1648,
        "a": 3240
      },
      {
        "p": 1645,
        "a": 2700
      },
      {
        "p": 1641,
        "a": 4368
      },
      {
        "p": 1638,
        "a": 2826
      }
    ],
    "asks": [
      {
        "p": 1668,
        "a": 108
      },
      {
        "p": 1671,
        "a": 4770
      },
      {
        "p": 1674,
        "a": 1128
      },
      {
        "p": 1678,
        "a": 2851
      },
      {
        "p": 1681,
        "a": 2087
      },
      {
        "p": 1684,
        "a": 2348
      },
      {
        "p": 1688,
        "a": 1142
      },
      {
        "p": 1691,
        "a": 361
      }
    ]
  },
  "trades": [
    {
      "t": "05.23.40",
      "type": "SELL",
      "p": 1665,
      "a": 1413
    },
    {
      "t": "05.23.30",
      "type": "BUY",
      "p": 1665,
      "a": 37
    },
    {
      "t": "05.23.25",
      "type": "BUY",
      "p": 1665,
      "a": 300
    },
    {
      "t": "05.23.20",
      "type": "SELL",
      "p": 1665,
      "a": 1839
    },
    {
      "t": "05.23.00",
      "type": "BUY",
      "p": 1665,
      "a": 1675
    },
    {
      "t": "05.22.45",
      "type": "SELL",
      "p": 1665,
      "a": 1440
    },
    {
      "t": "05.22.40",
      "type": "SELL",
      "p": 1665,
      "a": 1294
    },
    {
      "t": "05.22.35",
      "type": "BUY",
      "p": 1665,
      "a": 1167
    },
    {
      "t": "05.22.30",
      "type": "BUY",
      "p": 1665,
      "a": 705
    },
    {
      "t": "05.22.25",
      "type": "BUY",
      "p": 1665,
      "a": 1557
    },
    {
      "t": "05.22.20",
      "type": "BUY",
      "p": 1665,
      "a": 468
    },
    {
      "t": "05.22.15",
      "type": "BUY",
      "p": 1665,
      "a": 1853
    },
    {
      "t": "05.22.05",
      "type": "BUY",
      "p": 1665,
      "a": 753
    },
    {
      "t": "05.21.45",
      "type": "BUY",
      "p": 1665,
      "a": 727
    },
    {
      "t": "05.21.35",
      "type": "BUY",
      "p": 1665,
      "a": 663
    }
  ],
  "history": [
    {
      "t": "05.09.34",
      "p": 1665
    },
    {
      "t": "05.09.45",
      "p": 1665
    },
    {
      "t": "05.09.55",
      "p": 1665
    },
    {
      "t": "05.10.00",
      "p": 1665
    },
    {
      "t": "05.10.10",
      "p": 1665
    },
    {
      "t": "05.10.40",
      "p": 1665
    },
    {
      "t": "05.11.05",
      "p": 1665
    },
    {
      "t": "05.11.10",
      "p": 1665
    },
    {
      "t": "05.11.20",
      "p": 1665
    },
    {
      "t": "05.12.10",
      "p": 1665
    },
    {
      "t": "05.12.15",
      "p": 1665
    },
    {
      "t": "05.12.30",
      "p": 1665
    },
    {
      "t": "05.12.40",
      "p": 1665
    },
    {
      "t": "05.13.05",
      "p": 1665
    },
    {
      "t": "05.13.15",
      "p": 1665
    },
    {
      "t": "05.13.20",
      "p": 1665
    },
    {
      "t": "05.13.40",
      "p": 1665
    },
    {
      "t": "05.13.45",
      "p": 1665
    },
    {
      "t": "05.13.50",
      "p": 1665
    },
    {
      "t": "05.13.55",
      "p": 1665
    },
    {
      "t": "05.14.10",
      "p": 1665
    },
    {
      "t": "05.14.15",
      "p": 1665
    },
    {
      "t": "05.14.30",
      "p": 1665
    },
    {
      "t": "05.15.20",
      "p": 1665
    },
    {
      "t": "05.15.35",
      "p": 1665
    },
    {
      "t": "05.15.40",
      "p": 1665
    },
    {
      "t": "05.15.45",
      "p": 1665
    },
    {
      "t": "05.15.50",
      "p": 1665
    },
    {
      "t": "05.15.55",
      "p": 1665
    },
    {
      "t": "05.16.00",
      "p": 1665
    },
    {
      "t": "05.16.20",
      "p": 1665
    },
    {
      "t": "05.16.25",
      "p": 1665
    },
    {
      "t": "05.16.40",
      "p": 1665
    },
    {
      "t": "05.16.45",
      "p": 1665
    },
    {
      "t": "05.16.50",
      "p": 1665
    },
    {
      "t": "05.17.10",
      "p": 1665
    },
    {
      "t": "05.17.35",
      "p": 1665
    },
    {
      "t": "05.17.45",
      "p": 1665
    },
    {
      "t": "05.18.10",
      "p": 1665
    },
    {
      "t": "05.18.35",
      "p": 1665
    },
    {
      "t": "05.19.05",
      "p": 1665
    },
    {
      "t": "05.19.25",
      "p": 1665
    },
    {
      "t": "05.19.35",
      "p": 1665
    },
    {
      "t": "05.19.50",
      "p": 1665
    },
    {
      "t": "05.20.05",
      "p": 1665
    },
    {
      "t": "05.20.10",
      "p": 1665
    },
    {
      "t": "05.20.35",
      "p": 1665
    },
    {
      "t": "05.20.40",
      "p": 1665
    },
    {
      "t": "05.21.10",
      "p": 1665
    },
    {
      "t": "05.21.30",
      "p": 1665
    },
    {
      "t": "05.21.35",
      "p": 1665
    },
    {
      "t": "05.21.40",
      "p": 1665
    },
    {
      "t": "05.21.45",
      "p": 1665
    },
    {
      "t": "05.21.55",
      "p": 1665
    },
    {
      "t": "05.22.05",
      "p": 1665
    },
    {
      "t": "05.22.35",
      "p": 1665
    },
    {
      "t": "05.22.40",
      "p": 1665
    },
    {
      "t": "05.22.45",
      "p": 1665
    },
    {
      "t": "05.22.50",
      "p": 1665
    },
    {
      "t": "05.23.40",
      "p": 1665
    }
  ],
  "stats": {
    "total_investors": 1
  }
}