{
  "status": "MARKET_OPEN",
  "last_updated": 1764647320124,
  "readable_time": "2/12/2025, 03.48.40",
  "market": {
    "price": 2078,
    "trend": "📈 BULLISH (News)",
    "high": 2327,
    "low": 1828,
    "vol": 3668034,
    "mcap": 20780000000,
    "news": {
      "headline": "Laporan keuangan kuartal ini menunjukkan profit fantastis.",
      "type": "GOOD",
      "timestamp": 1764647074938
    }
  },
  "leaderboard": [
    {
      "name": "Big Boss",
      "wealth": 1002079296087
    }
  ],
  "orderBook": {
    "bids": [
      {
        "p": 2073,
        "a": 677
      },
      {
        "p": 2069,
        "a": 4072
      },
      {
        "p": 2065,
        "a": 1967
      },
      {
        "p": 2061,
        "a": 2767
      },
      {
        "p": 2057,
        "a": 1225
      },
      {
        "p": 2053,
        "a": 4020
      },
      {
        "p": 2048,
        "a": 3194
      },
      {
        "p": 2044,
        "a": 951
      }
    ],
    "asks": [
      {
        "p": 2082,
        "a": 3064
      },
      {
        "p": 2086,
        "a": 1973
      },
      {
        "p": 2090,
        "a": 4103
      },
      {
        "p": 2094,
        "a": 4800
      },
      {
        "p": 2098,
        "a": 3930
      },
      {
        "p": 2102,
        "a": 1732
      },
      {
        "p": 2107,
        "a": 123
      },
      {
        "p": 2111,
        "a": 3478
      }
    ]
  },
  "trades": [
    {
      "t": "03.48.30",
      "type": "BUY",
      "p": 2078,
      "a": 274
    },
    {
      "t": "03.48.20",
      "type": "BUY",
      "p": 2078,
      "a": 628
    },
    {
      "t": "03.48.00",
      "type": "SELL",
      "p": 2078,
      "a": 1104
    },
    {
      "t": "03.47.50",
      "type": "BUY",
      "p": 2078,
      "a": 389
    },
    {
      "t": "03.47.40",
      "type": "SELL",
      "p": 2078,
      "a": 529
    },
    {
      "t": "03.47.35",
      "type": "BUY",
      "p": 2078,
      "a": 989
    },
    {
      "t": "03.47.30",
      "type": "SELL",
      "p": 2078,
      "a": 1917
    },
    {
      "t": "03.47.25",
      "type": "BUY",
      "p": 2078,
      "a": 1275
    },
    {
      "t": "03.47.20",
      "type": "BUY",
      "p": 2078,
      "a": 268
    },
    {
      "t": "03.47.10",
      "type": "SELL",
      "p": 2078,
      "a": 805
    },
    {
      "t": "03.46.55",
      "type": "SELL",
      "p": 2078,
      "a": 1433
    },
    {
      "t": "03.46.50",
      "type": "SELL",
      "p": 2078,
      "a": 404
    },
    {
      "t": "03.46.40",
      "type": "BUY",
      "p": 2078,
      "a": 1153
    },
    {
      "t": "03.46.35",
      "type": "BUY",
      "p": 2078,
      "a": 737
    },
    {
      "t": "03.46.14",
      "type": "SELL",
      "p": 2078,
      "a": 113
    }
  ],
  "history": [
    {
      "t": "03.36.19",
      "p": 2003
    },
    {
      "t": "03.36.44",
      "p": 2003
    },
    {
      "t": "03.36.49",
      "p": 2003
    },
    {
      "t": "03.36.54",
      "p": 2003
    },
    {
      "t": "03.37.14",
      "p": 2003
    },
    {
      "t": "03.37.19",
      "p": 2003
    },
    {
      "t": "03.37.24",
      "p": 2003
    },
    {
      "t": "03.37.39",
      "p": 2003
    },
    {
      "t": "03.37.49",
      "p": 2003
    },
    {
      "t": "03.38.19",
      "p": 2003
    },
    {
      "t": "03.38.24",
      "p": 1962
    },
    {
      "t": "03.38.39",
      "p": 1962
    },
    {
      "t": "03.38.59",
      "p": 1962
    },
    {
      "t": "03.39.04",
      "p": 2001
    },
    {
      "t": "03.39.09",
      "p": 2001
    },
    {
      "t": "03.39.44",
      "p": 2001
    },
    {
      "t": "03.39.59",
      "p": 2001
    },
    {
      "t": "03.40.04",
      "p": 2021
    },
    {
      "t": "03.40.09",
      "p": 2021
    },
    {
      "t": "03.40.14",
      "p": 2021
    },
    {
      "t": "03.40.29",
      "p": 2021
    },
    {
      "t": "03.40.49",
      "p": 2021
    },
    {
      "t": "03.40.59",
      "p": 2021
    },
    {
      "t": "03.41.14",
      "p": 2021
    },
    {
      "t": "03.41.24",
      "p": 2021
    },
    {
      "t": "03.41.34",
      "p": 2021
    },
    {
      "t": "03.41.44",
      "p": 2021
    },
    {
      "t": "03.41.59",
      "p": 2021
    },
    {
      "t": "03.42.09",
      "p": 2021
    },
    {
      "t": "03.42.29",
      "p": 2021
    },
    {
      "t": "03.42.44",
      "p": 2021
    },
    {
      "t": "03.42.49",
      "p": 2061
    },
    {
      "t": "03.42.59",
      "p": 1999
    },
    {
      "t": "03.43.04",
      "p": 1999
    },
    {
      "t": "03.43.09",
      "p": 1999
    },
    {
      "t": "03.43.24",
      "p": 1999
    },
    {
      "t": "03.43.39",
      "p": 1999
    },
    {
      "t": "03.43.44",
      "p": 1999
    },
    {
      "t": "03.43.49",
      "p": 1999
    },
    {
      "t": "03.43.59",
      "p": 1999
    },
    {
      "t": "03.44.09",
      "p": 1999
    },
    {
      "t": "03.44.19",
      "p": 1999
    },
    {
      "t": "03.44.39",
      "p": 2078
    },
    {
      "t": "03.44.44",
      "p": 2078
    },
    {
      "t": "03.44.54",
      "p": 2078
    },
    {
      "t": "03.45.09",
      "p": 2078
    },
    {
      "t": "03.45.29",
      "p": 2078
    },
    {
      "t": "03.45.49",
      "p": 2078
    },
    {
      "t": "03.45.54",
      "p": 2078
    },
    {
      "t": "03.45.59",
      "p": 2078
    },
    {
      "t": "03.46.14",
      "p": 2078
    },
    {
      "t": "03.46.20",
      "p": 2078
    },
    {
      "t": "03.46.30",
      "p": 2078
    },
    {
      "t": "03.46.35",
      "p": 2078
    },
    {
      "t": "03.47.00",
      "p": 2078
    },
    {
      "t": "03.47.15",
      "p": 2078
    },
    {
      "t": "03.47.30",
      "p": 2078
    },
    {
      "t": "03.47.45",
      "p": 2078
    },
    {
      "t": "03.47.50",
      "p": 2078
    },
    {
      "t": "03.48.00",
      "p": 2078
    }
  ],
  "stats": {
    "total_investors": 1
  }
}